Python3BiaozhunKuShilijiaocheng/README.md
Python3BiaozhunKuShilijiaocheng/__init__.py
Python3BiaozhunKuShilijiaocheng/__main__.py
Python3BiaozhunKuShilijiaocheng/file.epub
Python3BiaozhunKuShilijiaocheng/index.html
Python3BiaozhunKuShilijiaocheng/css/__init__.py
Python3BiaozhunKuShilijiaocheng/css/annotations.css
Python3BiaozhunKuShilijiaocheng/css/main.css
Python3BiaozhunKuShilijiaocheng/css/normalize.css
Python3BiaozhunKuShilijiaocheng/css/popup.css
Python3BiaozhunKuShilijiaocheng/font/__init__.py
Python3BiaozhunKuShilijiaocheng/font/fontello.eot
Python3BiaozhunKuShilijiaocheng/font/fontello.svg
Python3BiaozhunKuShilijiaocheng/font/fontello.ttf
Python3BiaozhunKuShilijiaocheng/font/fontello.woff
Python3BiaozhunKuShilijiaocheng/img/__init__.py
Python3BiaozhunKuShilijiaocheng/img/annotator-glyph-sprite.png
Python3BiaozhunKuShilijiaocheng/img/annotator-icon-sprite.png
Python3BiaozhunKuShilijiaocheng/img/apple-touch-icon.png
Python3BiaozhunKuShilijiaocheng/img/cancelfullscreen.png
Python3BiaozhunKuShilijiaocheng/img/close.png
Python3BiaozhunKuShilijiaocheng/img/fullscreen.png
Python3BiaozhunKuShilijiaocheng/img/loader.gif
Python3BiaozhunKuShilijiaocheng/img/menu-icon.png
Python3BiaozhunKuShilijiaocheng/img/save.png
Python3BiaozhunKuShilijiaocheng/img/saved.png
Python3BiaozhunKuShilijiaocheng/img/settings-s.png
Python3BiaozhunKuShilijiaocheng/img/settings.png
Python3BiaozhunKuShilijiaocheng/img/star.png
Python3BiaozhunKuShilijiaocheng/js/__init__.py
Python3BiaozhunKuShilijiaocheng/js/epub.js
Python3BiaozhunKuShilijiaocheng/js/epub.min.js
Python3BiaozhunKuShilijiaocheng/js/epub.min.map
Python3BiaozhunKuShilijiaocheng/js/hooks.min.js
Python3BiaozhunKuShilijiaocheng/js/hooks.min.map
Python3BiaozhunKuShilijiaocheng/js/reader.js
Python3BiaozhunKuShilijiaocheng/js/reader.js.map
Python3BiaozhunKuShilijiaocheng/js/reader.min.js
Python3BiaozhunKuShilijiaocheng/js/reader.min.map
Python3BiaozhunKuShilijiaocheng/js/hooks/__init__.py
python_3_biaozhun_ku_shilijiaocheng-2024.3.5.0.dist-info/METADATA
python_3_biaozhun_ku_shilijiaocheng-2024.3.5.0.dist-info/WHEEL
python_3_biaozhun_ku_shilijiaocheng-2024.3.5.0.dist-info/entry_points.txt
python_3_biaozhun_ku_shilijiaocheng-2024.3.5.0.dist-info/top_level.txt
python_3_biaozhun_ku_shilijiaocheng-2024.3.5.0.dist-info/RECORD
